pyproject_examples/__init__.py
pyproject_examples/example_configs.py
pyproject_examples/py.typed
pyproject_examples/utils.py
pyproject_examples-2023.6.30.dist-info/LICENSE
pyproject_examples-2023.6.30.dist-info/METADATA
pyproject_examples-2023.6.30.dist-info/WHEEL
pyproject_examples-2023.6.30.dist-info/entry_points.txt
pyproject_examples-2023.6.30.dist-info/RECORD
