Metadata-Version: 2.1
Name: pyproject-examples
Version: 2023.6.30
Summary: Example pyproject.toml configs for testing.
Author-email: Dominic Davis-Foster <dominic@davis-foster.co.uk>
License: MIT
Home-page: https://github.com/repo-helper/pyproject-examples
Project-URL: Issue Tracker, https://github.com/repo-helper/pyproject-examples/issues
Project-URL: Source Code, https://github.com/repo-helper/pyproject-examples
Platform: Windows
Platform: macOS
Platform: Linux
Classifier: License :: OSI Approved :: MIT License
Classifier: Operating System :: OS Independent
Classifier: Programming Language :: Python
Classifier: Programming Language :: Python :: 3 :: Only
Classifier: Programming Language :: Python :: 3.8
Classifier: Programming Language :: Python :: Implementation :: CPython
Classifier: Typing :: Typed
Requires-Python: >=3.6
Requires-Dist: coincidence>=0.4.0
Requires-Dist: dom-toml>=0.4.0
Requires-Dist: packaging>=21.3
Requires-Dist: pytest>=6.2.3
